bookdog/__init__.py
bookdog/database.py
bookdog/main.py
bookdog/model.py
bookdog/views.py
bookdog-1.0.1.dist-info/licenses/LICENSE
bookdog-1.0.1.dist-info/METADATA
bookdog-1.0.1.dist-info/WHEEL
bookdog-1.0.1.dist-info/entry_points.txt
bookdog-1.0.1.dist-info/top_level.txt
bookdog-1.0.1.dist-info/RECORD
