Metadata-Version: 2.4
Name: bookdog
Version: 1.0.1
Summary: Track books you've read or listened to
Home-page: https://github.com/jima80525/bookdog
Author: Jim Anderson
Author-email: Jim Anderson <jima.coding@gmail.com>
License: MIT License
Project-URL: Home, https://github.com/jima80525/bookdog
Classifier: License :: OSI Approved :: MIT License
Classifier: Programming Language :: Python
Classifier: Programming Language :: Python :: 3
Classifier: Programming Language :: Python :: 3.8
Requires-Python: >=3.8.0
License-File: LICENSE
Requires-Dist: PyQt5==5.15.7
Requires-Dist: PyQt5-Qt5==5.15.2
Requires-Dist: PyQt5-sip==12.11.0
Provides-Extra: dev
Requires-Dist: black; extra == "dev"
Requires-Dist: bump2version>=1.0.1; extra == "dev"
Requires-Dist: bumpversion>=0.6.0; extra == "dev"
Requires-Dist: invoke>=1.7.3; extra == "dev"
Dynamic: author
Dynamic: home-page
Dynamic: license-file
Dynamic: requires-python
Dynamic: summary
